{
    "id": 81139702,
    "name": "The Hallucination",
    "author": "SyQual",
    "creators": ["SyQual", "VoTcHi"],
    "verifier": "wPopoff",
    "verification": "https://www.youtube.com/watch?v=fdp8CvI5uUw",
    "percentToQualify": "100",
    "password": "Free to Copy",
    "records": [
        {
            "user": "Cuatrocientos",
            "link": "https://www.youtube.com/watch?v=yfXrv702bmU",
            "percent": 100,
            "hz": 360
        },
        {
            "user": "Superjavicon",
            "link": "https://youtu.be/2R0LIuLzg-4?si=f8XXDkDejRAp1SOw",
            "percent": 100,
            "hz": 360
        },
        {
            "user": "Laser",
            "link": "https://www.youtube.com/watch?v=wlwXCpRYuNc",
            "percent": 100,
            "hz": 360
        },
        {
            "user": "stillsouless",
            "link": "https://youtu.be/h7mmP-nwUv4?si=RTvVK3jjBnJlmzVK",
            "percent": 100,
            "hz": 360
        },
        {
            "user": "Vorten",
            "link": "https://www.youtube.com/watch?v=nIQ0MQOG5H8",
            "percent": 100,
            "hz": 360
        },
        {
            "user": "moliklee",
            "link": "https://www.youtube.com/watch?v=tHWGukI1Xu0",
            "percent": 100,
            "hz": 360
        },
        {
            "user": "Kole",
            "link": "https://youtu.be/oTBEth7-joA?si=qyhfZ0oRYsG1bmko",
            "percent": 100,
            "hz": 360
        },
        {
            "user": "Serpentical",
            "link": "https://youtu.be/UST8Ge6qR4A?si=Yg7nPinhdQtmUVWe",
            "percent": 100,
            "hz": 360
        }
    ]
}
